AutoROM/AutoROM.py
AutoROM/__init__.py
AutoROM/roms/__init__.py
AutoROM-0.6.1.dist-info/LICENSE.txt
AutoROM-0.6.1.dist-info/METADATA
AutoROM-0.6.1.dist-info/WHEEL
AutoROM-0.6.1.dist-info/entry_points.txt
AutoROM-0.6.1.dist-info/top_level.txt
AutoROM-0.6.1.dist-info/RECORD
