Metadata-Version: 2.1
Name: AutoROM
Version: 0.6.1
Summary: Automated installation of Atari ROMs for Gym/ALE-Py
Home-page: https://github.com/Farama-Foundation/AutoROM
Author: Farama Foundation
Author-email: contact@farama.org
License: MIT
Keywords: Reinforcement Learning,game,RL,AI,gym
Classifier: Programming Language :: Python :: 3.7
Classifier: Programming Language :: Python :: 3.8
Classifier: Programming Language :: Python :: 3.9
Classifier: Programming Language :: Python :: 3.10
Classifier: License :: OSI Approved :: MIT License
Classifier: Operating System :: OS Independent
Requires-Python: >=3.7
Provides-Extra: accept-rom-license
License-File: LICENSE.txt
